singleccellkit/__init__.py
singleccellkit/pl/__init__.py
singleccellkit/pl/_emmbeding.py
singleccellkit/pl/_stat.py
singleccellkit/pp/__init__.py
singleccellkit/pp/_normalization.py
singleccellkit/pp/_qc.py
singleccellkit/tl/__init__.py
singleccellkit/tl/_integration.py
singleccellkit/tl/_trajectory.py
singleccellkit/tl/cell_type_annotation.py
singleccellkit/tl/compositional_analysis.py
singleccellkit/tl/gene_level_analysis.py
singleccellkit/tl/utils.py
singleccellkit-0.1.0.dist-info/LICENSE
singleccellkit-0.1.0.dist-info/METADATA
singleccellkit-0.1.0.dist-info/WHEEL
singleccellkit-0.1.0.dist-info/RECORD
