Metadata-Version: 2.1
Name: SinglecCellKit
Version: 0.1.0
Summary: single cell multi-omics data analysis kit
Author: 生信探索 bioquest
Author-email: aubot@hotmail.com
Requires-Python: >=3.9,<4.0
Classifier: Programming Language :: Python :: 3
Classifier: Programming Language :: Python :: 3.9
Classifier: Programming Language :: Python :: 3.10
Classifier: Programming Language :: Python :: 3.11
Classifier: Programming Language :: Python :: 3.12
Requires-Dist: numpy (>=1.23,<2.0)
Requires-Dist: pandas (>=1.5,<2.0)
Requires-Dist: pydeseq2 (>=0.4.9,<0.5.0)
Requires-Dist: scanpy (>=1.10,<2.0)
